setup.py
dnb/__init__.py
dnb.egg-info/PKG-INFO
dnb.egg-info/SOURCES.txt
dnb.egg-info/dependency_links.txt
dnb.egg-info/not-zip-safe
dnb.egg-info/top_level.txt