Metadata-Version: 1.0
Name: dnb
Version: 0.0.1
Summary: D&B Direct API
Home-page: UNKNOWN
Author: Bülent Aldemir
Author-email: buelent@e-evolution.de
License: MIT
Platform: UNKNOWN
